murdaws/__init__.py
murdaws/murd_ddb.py
murdaws-0.0.1.0.dist-info/METADATA
murdaws-0.0.1.0.dist-info/WHEEL
murdaws-0.0.1.0.dist-info/top_level.txt
murdaws-0.0.1.0.dist-info/RECORD
