Metadata-Version: 2.1
Name: murdaws
Version: 0.0.1.0
Summary: AWS Murd moudles
Home-page: https://gitlab.com/musingsole/murdaws
Author: musingsole
Author-email: musingsole@gmail.com
License: UNKNOWN
Platform: UNKNOWN
Classifier: Programming Language :: Python :: 3
Classifier: License :: OSI Approved :: MIT License
Classifier: Operating System :: OS Independent
Requires-Dist: jod
Requires-Dist: murd
Requires-Dist: boto3
